Workbook

Sheet 1. INPUT
A1: OAKAI KPI Dashboard
A3: Prepared for: EG SEOW / Founder, OAKAI SDN BHD
A5: INSTRUCTIONS: All BLUE cells are INPUTS — fill from client data. All other cells auto-calculate.
A7: 1.1 Product Portfolio Input
A9: Product ID | B9: Product Name | C9: Std Cycle Time (sec) | D9: Week 1 | E9: Week 2 | F9: Week 3 | G9: Week 4 | H9: Week 5 | I9: Unit Price (RM) | J9: Contribution Margin / Unit (RM)
A10: 1 | B10: Product A | C10: 9 | D10: 9000 | E10: 0 | F10: 5000 | G10: 0 | H10: 9000 | I10: 0 | J10: 1500
A11: 2 | B11: Product B | C11: 9.8 | D11: 8000 | E11: 9000 | F11: 0 | G11: 6000 | H11: 8000 | I11: 9000 | J11: 0 | K11: 1800
A12: 3 | B12: Product C | C12: 9.6 | D12: 10000 | E12: 8000 | F12: 9000 | G12: 0 | H12: 10000 | I12: 8000 | J12: 9000 | K12: 2200
A13: 4 | B13: Product D | C13: 11 | D13: 13000 | E13: 10000 | F13: 8000 | G13: 9000 | H13: 9000 | I13: 8000 | J13: 0 | K13: 2500
A14: 5 | B14: Product E | C14: 10.8 | D14: 5000 | E14: 13000 | F14: 10000 | G14: 8000 | H14: 5000 | I14: 11000 | J14: 10000 | K14: 1900
A15: 6 | B15: Product F | C15: 10.5 | D15: 0 | E15: 5000 | F15: 13000 | G15: 0 | H15: 0 | I15: 5000 | J15: 13000 | K15: 1600
A16: 7 | B16: Product G | C16: 9 | D16: 0 | E16: 3000 | F16: 6000 | G16: 11000 | H16: 0 | I16: 0 | J16: 5000 | K16: 1700
A17: 8 | B17: Product H | C17: 9.2 | D17: 0 | E17: 0 | F17: 0 | G17: 5000 | H17: 0 | I17: 0 | J17: 0 | K17: 2100
B18: TOTAL | D18: =SUM(D10:D17) | E18: =SUM(E10:E17) | F18: =SUM(F10:F17) | G18: =SUM(G10:G17) | H18: =SUM(H10:H17) | I18: =SUM(I10:I17)
A20: Product Count | B20: 8

Sheet 2. ASSUMPTIONS
A1: 2. Assumptions & Operational Parameters
A3: Prepared for: EG SEOW
A5: Parameter | B5: Value | C5: Unit | D5: Description | E5: Source
A6: Hours / Shift | B6: 8 | C6: hours | D6: Working hours per shift | E6: Input
A7: Shift / Day | B7: 3 | C7: shifts | D7: Production shifts per day | E7: Input
A8: Operation Days / Week | B8: 7 | C8: days | D8: Operating days per week (Mon-Sun) | E8: Input
A9: Weeks / Year | B9: 52 | C9: weeks | D9: Calendar weeks analyzed | E9: Input
A10: Total Production Planned Time (sec) | B10: =B6*B7*B8*3600*52 | C10: seconds | D10: Annual planned production time | E10: Auto
A11: Equipment Target Utilization | B11: 90 | C11: % | D11: OEE availability target | E11: Best Practice
A12: Yield Loss Target | B12: 5 | C12: % | D12: Quality target (max defect rate) | E12: Best Practice
A13: Rework Loss Target | B13: 3 | C13: % | D13: Rework target | E13: Best Practice
A14: Rework Cost / Unit | B14: 150 | C14: RM | D14: Average rework cost per unit | E14: Input
A15: Labor Rate | B15: 30 | C15: RM/hr | D15: Average labor rate | E15: Input
A16: Material Cost / Unit | B16: 500 | C16: RM | D16: Average material cost per unit | E16: Input
A17: Utility Cost / Unit | B17: 50 | C17: RM | D17: Average utility cost per unit | E17: Input
A18: Contribution Margin / Unit | B18: 2000 | C18: RM | D18: Revenue - variable cost per unit | E18: Input

Sheet 3. LOSS_ANALYSIS
A1: 3. Loss Analysis — Opportunity Identification
A3: Prepared for: EG SEOW
A5: Loss Category | B5: Product ID | C5: Week 1 | D5: Week 2 | E5: Week 3 | F5: Week 4 | G5: Week 5 | H5: Annual $ Impact (RM)
A6: USDT - Machine Failure | B6: 1 | C6: '1. INPUT'!D10 | D6: '1. INPUT'!E10 | E6: '1. INPUT'!F10 | F6: '1. INPUT'!G10 | G6: '1. INPUT'!H10 | H6: =SUM(C6:G6)*52
B7: 2 | C7: '1. INPUT'!D11 | D7: '1. INPUT'!E11 | E7: '1. INPUT'!F11 | F7: '1. INPUT'!G11 | G7: '1. INPUT'!H11 | H7: =SUM(C7:G7)*52
B8: 3 | C8: '1. INPUT'!D12 | D8: '1. INPUT'!E12 | E8: '1. INPUT'!F12 | F8: '1. INPUT'!G12 | G8: '1. INPUT'!H12 | H8: =SUM(C8:G8)*52
B9: 4 | C9: '1. INPUT'!D13 | D9: '1. INPUT'!E13 | E9: '1. INPUT'!F13 | F9: '1. INPUT'!G13 | G9: '1. INPUT'!H13 | H9: =SUM(C9:G9)*52
B10: 5 | C10: '1. INPUT'!D14 | D10: '1. INPUT'!E14 | E10: '1. INPUT'!F14 | F10: '1. INPUT'!G14 | G10: '1. INPUT'!H14 | H10: =SUM(C10:G10)*52
B11: 6 | C11: '1. INPUT'!D15 | D11: '1. INPUT'!E15 | E11: '1. INPUT'!F15 | F11: '1. INPUT'!G15 | G11: '1. INPUT'!H15 | H11: =SUM(C11:G11)*52
B12: 7 | C12: '1. INPUT'!D16 | D12: '1. INPUT'!E16 | E12: '1. INPUT'!F16 | F12: '1. INPUT'!G16 | G12: '1. INPUT'!H16 | H12: =SUM(C12:G12)*52
B13: 8 | C13: '1. INPUT'!D17 | D13: '1. INPUT'!E17 | E13: '1. INPUT'!F17 | F13: '1. INPUT'!G17 | G13: '1. INPUT'!H17 | H13: =SUM(C13:G13)*52
A15: USDT - Machine Assist | B15: 1 | C15: '1. INPUT'!D10 | D15: '1. INPUT'!E10 | E15: '1. INPUT'!F10 | F15: '1. INPUT'!G10 | G15: '1. INPUT'!H10 | H15: =SUM(C15:G15)*52
B16: 2 | C16: '1. INPUT'!D11 | D16: '1. INPUT'!E11 | E16: '1. INPUT'!F11 | F16: '1. INPUT'!G11 | G16: '1. INPUT'!H11 | H16: =SUM(C16:G16)*52
B17: 3 | C17: '1. INPUT'!D12 | D17: '1. INPUT'!E12 | E17: '1. INPUT'!F12 | F17: '1. INPUT'!G12 | G17: '1. INPUT'!H12 | H17: =SUM(C17:G17)*52
B18: 4 | C18: '1. INPUT'!D13 | D18: '1. INPUT'!E13 | E18: '1. INPUT'!F13 | F18: '1. INPUT'!G13 | G18: '1. INPUT'!H13 | H18: =SUM(C18:G18)*52
B19: 5 | C19: '1. INPUT'!D14 | D19: '1. INPUT'!E14 | E19: '1. INPUT'!F14 | F19: '1. INPUT'!G14 | G19: '1. INPUT'!H14 | H19: =SUM(C19:G19)*52
B20: 6 | C20: '1. INPUT'!D15 | D20: '1. INPUT'!E15 | E20: '1. INPUT'!F15 | F20: '1. INPUT'!G15 | G20: '1. INPUT'!H15 | H20: =SUM(C20:G20)*52
B21: 7 | C21: '1. INPUT'!D16 | D21: '1. INPUT'!E16 | E21: '1. INPUT'!F16 | F21: '1. INPUT'!G16 | G21: '1. INPUT'!H16 | H21: =SUM(C21:G21)*52
B22: 8 | C22: '1. INPUT'!D17 | D22: '1. INPUT'!E17 | E22: '1. INPUT'!F17 | F22: '1. INPUT'!G17 | G22: '1. INPUT'!H17 | H22: =SUM(C22:G22)*52
A24: Quality Loss - Defect | B24: 1 | C24: '1. INPUT'!D10 | D24: '1. INPUT'!E10 | E24: '1. INPUT'!F10 | F24: '1. INPUT'!G10 | G24: '1. INPUT'!H10 | H24: =SUM(C24:G24)*52
B25: 2 | C25: '1. INPUT'!D11 | D25: '1. INPUT'!E11 | E25: '1. INPUT'!F11 | F25: '1. INPUT'!G11 | G25: '1. INPUT'!H11 | H25: =SUM(C25:G25)*52
B26: 3 | C26: '1. INPUT'!D12 | D26: '1. INPUT'!E12 | E26: '1. INPUT'!F12 | F26: '1. INPUT'!G12 | G26: '1. INPUT'!H12 | H26: =SUM(C26:G26)*52
B27: 4 | C27: '1. INPUT'!D13 | D27: '1. INPUT'!E13 | E27: '1. INPUT'!F13 | F27: '1. INPUT'!G13 | G27: '1. INPUT'!H13 | H27: =SUM(C27:G27)*52
B28: 5 | C28: '1. INPUT'!D14 | D28: '1. INPUT'!E14 | E28: '1. INPUT'!F14 | F28: '1. INPUT'!G14 | G28: '1. INPUT'!H14 | H28: =SUM(C28:G28)*52
B29: 6 | C29: '1. INPUT'!D15 | D29: '1. INPUT'!E15 | E29: '1. INPUT'!F15 | F29: '1. INPUT'!G15 | G29: '1. INPUT'!H15 | H29: =SUM(C29:G29)*52
B30: 7 | C30: '1. INPUT'!D16 | D30: '1. INPUT'!E16 | E30: '1. INPUT'!F16 | F30: '1. INPUT'!G16 | G30: '1. INPUT'!H16 | H30: =SUM(C30:G30)*52
B31: 8 | C31: '1. INPUT'!D17 | D31: '1. INPUT'!E17 | E31: '1. INPUT'!F17 | F31: '1. INPUT'!G17 | G31: '1. INPUT'!H17 | H31: =SUM(C31:G31)*52
A33: Quality Loss - Rework | B33: 1 | C33: '1. INPUT'!D10 | D33: '1. INPUT'!E10 | E33: '1. INPUT'!F10 | F33: '1. INPUT'!G10 | G33: '1. INPUT'!H10 | H33: =SUM(C33:G33)*52
B34: 2 | C34: '1. INPUT'!D11 | D34: '1. INPUT'!E11 | E34: '1. INPUT'!F11 | F34: '1. INPUT'!G11 | G34: '1. INPUT'!H11 | H34: =SUM(C34:G34)*52
B35: 3 | C35: '1. INPUT'!D12 | D35: '1. INPUT'!E12 | E35: '1. INPUT'!F12 | F35: '1. INPUT'!G12 | G35: '1. INPUT'!H12 | H35: =SUM(C35:G35)*52
B36: 4 | C36: '1. INPUT'!D13 | D36: '1. INPUT'!E13 | E36: '1. INPUT'!F13 | F36: '1. INPUT'!G13 | G36: '1. INPUT'!H13 | H36: =SUM(C36:G36)*52
B37: 5 | C37: '1. INPUT'!D14 | D37: '1. INPUT'!E14 | E37: '1. INPUT'!F14 | F37: '1. INPUT'!G14 | G37: '1. INPUT'!H14 | H37: =SUM(C37:G37)*52
B38: 6 | C38: '1. INPUT'!D15 | D38: '1. INPUT'!E15 | E38: '1. INPUT'!F15 | F38: '1. INPUT'!G15 | G38: '1. INPUT'!H15 | H38: =SUM(C38:G38)*52
B39: 7 | C39: '1. INPUT'!D16 | D39: '1. INPUT'!E16 | E39: '1. INPUT'!F16 | F39: '1. INPUT'!G16 | G39: '1. INPUT'!H16 | H39: =SUM(C39:G39)*52
B40: 8 | C40: '1. INPUT'!D17 | D40: '1. INPUT'!E17 | E40: '1. INPUT'!F17 | F40: '1. INPUT'!G17 | G40: '1. INPUT'!H17 | H40: =SUM(C40:G40)*52
A42: Speed Loss | B42: 1 | C42: '1. INPUT'!D10 | D42: '1. INPUT'!E10 | E42: '1. INPUT'!F10 | F42: '1. INPUT'!G10 | G42: '1. INPUT'!H10 | H42: =SUM(C42:G42)*52
B43: 2 | C43: '1. INPUT'!D11 | D43: '1. INPUT'!E11 | E43: '1. INPUT'!F11 | F43: '1. INPUT'!G11 | G43: '1. INPUT'!H11 | H43: =SUM(C43:G43)*52
B44: 3 | C44: '1. INPUT'!D12 | D44: '1. INPUT'!E12 | E44: '1. INPUT'!F12 | F44: '1. INPUT'!G12 | G44: '1. INPUT'!H12 | H44: =SUM(C44:G44)*52
B45: 4 | C45: '1. INPUT'!D13 | D45: '1. INPUT'!E13 | E45: '1. INPUT'!F13 | F45: '1. INPUT'!G13 | G45: '1. INPUT'!H13 | H45: =SUM(C45:G45)*52
B46: 5 | C46: '1. INPUT'!D14 | D46: '1. INPUT'!E14 | E46: '1. INPUT'!F14 | F46: '1. INPUT'!G14 | G46: '1. INPUT'!H14 | H46: =SUM(C46:G46)*52
B47: 6 | C47: '1. INPUT'!D15 | D47: '1. INPUT'!E15 | E47: '1. INPUT'!F15 | F47: '1. INPUT'!G15 | G47: '1. INPUT'!H15 | H47: =SUM(C47:G47)*52
B48: 7 | C48: '1. INPUT'!D16 | D48: '1. INPUT'!E16 | E48: '1. INPUT'!F16 | F48: '1. INPUT'!G16 | G48: '1. INPUT'!H16 | H48: =SUM(C48:G48)*52
B49: 8 | C49: '1. INPUT'!D17 | D49: '1. INPUT'!E17 | E49: '1. INPUT'!F17 | F49: '1. INPUT'!G17 | G49: '1. INPUT'!H17 | H49: =SUM(C49:G49)*52
A51: Labor Loss | B51: 1 | C51: '1. INPUT'!D10 | D51: '1. INPUT'!E10 | E51: '1. INPUT'!F10 | F51: '1. INPUT'!G10 | G51: '1. INPUT'!H10 | H51: =SUM(C51:G51)*52
B52: 2 | C52: '1. INPUT'!D11 | D52: '1. INPUT'!E11 | E52: '1. INPUT'!F11 | F52: '1. INPUT'!G11 | G52: '1. INPUT'!H11 | H52: =SUM(C52:G52)*52
B53: 3 | C53: '1. INPUT'!D12 | D53: '1. INPUT'!E12 | E53: '1. INPUT'!F12 | F53: '1. INPUT'!G12 | G53: '1. INPUT'!H12 | H53: =SUM(C53:G53)*52
B54: 4 | C54: '1. INPUT'!D13 | D54: '1. INPUT'!E13 | E54: '1. INPUT'!F13 | F54: '1. INPUT'!G13 | G54: '1. INPUT'!H13 | H54: =SUM(C54:G54)*52
B55: 5 | C55: '1. INPUT'!D14 | D55: '1. INPUT'!E14 | E55: '1. INPUT'!F14 | F55: '1. INPUT'!G14 | G55: '1. INPUT'!H14 | H55: =SUM(C55:G55)*52
B56: 6 | C56: '1. INPUT'!D15 | D56: '1. INPUT'!E15 | E56: '1. INPUT'!F15 | F56: '1. INPUT'!G15 | G56: '1. INPUT'!H15 | H56: =SUM(C56:G56)*52
B57: 7 | C57: '1. INPUT'!D16 | D57: '1. INPUT'!E16 | E57: '1. INPUT'!F16 | F57: '1. INPUT'!G16 | G57: '1. INPUT'!H16 | H57: =SUM(C57:G57)*52
B58: 8 | C58: '1. INPUT'!D17 | D58: '1. INPUT'!E17 | E58: '1. INPUT'!F17 | F58: '1. INPUT'!G17 | G58: '1. INPUT'!H17 | H58: =SUM(C58:G58)*52
A60: Utility Waste | B60: 1 | C60: '1. INPUT'!D10 | D60: '1. INPUT'!E10 | E60: '1. INPUT'!F10 | F60: '1. INPUT'!G10 | G60: '1. INPUT'!H10 | H60: =SUM(C60:G60)*52
B61: 2 | C61: '1. INPUT'!D11 | D61: '1. INPUT'!E11 | E61: '1. INPUT'!F11 | F61: '1. INPUT'!G11 | G61: '1. INPUT'!H11 | H61: =SUM(C61:G61)*52
B62: 3 | C62: '1. INPUT'!D12 | D62: '1. INPUT'!E12 | E62: '1. INPUT'!F12 | F62: '1. INPUT'!G12 | G62: '1. INPUT'!H12 | H62: =SUM(C62:G62)*52
B63: 4 | C63: '1. INPUT'!D13 | D63: '1. INPUT'!E13 | E63: '1. INPUT'!F13 | F63: '1. INPUT'!G13 | G63: '1. INPUT'!H13 | H63: =SUM(C63:G63)*52
B64: 5 | C64: '1. INPUT'!D14 | D64: '1. INPUT'!E14 | E64: '1. INPUT'!F14 | F64: '1. INPUT'!G14 | G64: '1. INPUT'!H14 | H64: =SUM(C64:G64)*52
B65: 6 | C65: '1. INPUT'!D15 | D65: '1. INPUT'!E15 | E65: '1. INPUT'!F15 | F65: '1. INPUT'!G15 | G65: '1. INPUT'!H15 | H65: =SUM(C65:G65)*52
B66: 7 | C66: '1. INPUT'!D16 | D66: '1. INPUT'!E16 | E66: '1. INPUT'!F16 | F66: '1. INPUT'!G16 | G66: '1. INPUT'!H16 | H66: =SUM(C66:G66)*52
B67: 8 | C67: '1. INPUT'!D17 | D67: '1. INPUT'!E17 | E67: '1. INPUT'!F17 | F67: '1. INPUT'!G17 | G67: '1. INPUT'!H17 | H67: =SUM(C67:G67)*52
A69: Customer Return | B69: 1 | C69: '1. INPUT'!D10 | D69: '1. INPUT'!E10 | E69: '1. INPUT'!F10 | F69: '1. INPUT'!G10 | G69: '1. INPUT'!H10 | H69: =SUM(C69:G69)*52
B70: 2 | C70: '1. INPUT'!D11 | D70: '1. INPUT'!E11 | E70: '1. INPUT'!F11 | F70: '1. INPUT'!G11 | G70: '1. INPUT'!H11 | H70: =SUM(C70:G70)*52
B71: 3 | C71: '1. INPUT'!D12 | D71: '1. INPUT'!E12 | E71: '1. INPUT'!F12 | F71: '1. INPUT'!G12 | G71: '1. INPUT'!H12 | H71: =SUM(C71:G71)*52
B72: 4 | C72: '1. INPUT'!D13 | D72: '1. INPUT'!E13 | E72: '1. INPUT'!F13 | F72: '1. INPUT'!G13 | G72: '1. INPUT'!H13 | H72: =SUM(C72:G72)*52
B73: 5 | C73: '1. INPUT'!D14 | D73: '1. INPUT'!E14 | E73: '1. INPUT'!F14 | F73: '1. INPUT'!G14 | G73: '1. INPUT'!H14 | H73: =SUM(C73:G73)*52
B74: 6 | C74: '1. INPUT'!D15 | D74: '1. INPUT'!E15 | E74: '1. INPUT'!F15 | F74: '1. INPUT'!G15 | G74: '1. INPUT'!H15 | H74: =SUM(C74:G74)*52
B75: 7 | C75: '1. INPUT'!D16 | D75: '1. INPUT'!E16 | E75: '1. INPUT'!F16 | F75: '1. INPUT'!G16 | G75: '1. INPUT'!H16 | H75: =SUM(C75:G75)*52
B76: 8 | C76: '1. INPUT'!D17 | D76: '1. INPUT'!E17 | E76: '1. INPUT'!F17 | F76: '1. INPUT'!G17 | G76: '1. INPUT'!H17 | H76: =SUM(C76:G76)*52
A78: Material Waste | B78: 1 | C78: '1. INPUT'!D10 | D78: '1. INPUT'!E10 | E78: '1. INPUT'!F10 | F78: '1. INPUT'!G10 | G78: '1. INPUT'!H10 | H78: =SUM(C78:G78)*52
B79: 2 | C79: '1. INPUT'!D11 | D79: '1. INPUT'!E11 | E79: '1. INPUT'!F11 | F79: '1. INPUT'!G11 | G79: '1. INPUT'!H11 | H79: =SUM(C79:G79)*52
B80: 3 | C80: '1. INPUT'!D12 | D80: '1. INPUT'!E12 | E80: '1. INPUT'!F12 | F80: '1. INPUT'!G12 | G80: '1. INPUT'!H12 | H80: =SUM(C80:G80)*52
B81: 4 | C81: '1. INPUT'!D13 | D81: '1. INPUT'!E13 | E81: '1. INPUT'!F13 | F81: '1. INPUT'!G13 | G81: '1. INPUT'!H13 | H81: =SUM(C81:G81)*52
B82: 5 | C82: '1. INPUT'!D14 | D82: '1. INPUT'!E14 | E82: '1. INPUT'!F14 | F82: '1. INPUT'!G14 | G82: '1. INPUT'!H14 | H82: =SUM(C82:G82)*52
B83: 6 | C83: '1. INPUT'!D15 | D83: '1. INPUT'!E15 | E83: '1. INPUT'!F15 | F83: '1. INPUT'!G15 | G83: '1. INPUT'!H15 | H83: =SUM(C83:G83)*52
B84: 7 | C84: '1. INPUT'!D16 | D84: '1. INPUT'!E16 | E84: '1. INPUT'!F16 | F84: '1. INPUT'!G16 | G84: '1. INPUT'!H16 | H84: =SUM(C84:G84)*52
B85: 8 | C85: '1. INPUT'!D17 | D85: '1. INPUT'!E17 | E85: '1. INPUT'!F17 | F85: '1. INPUT'!G17 | G85: '1. INPUT'!H17 | H85: =SUM(C85:G85)*52
A87: Tooling/Consumables | B87: 1 | C87: '1. INPUT'!D10 | D87: '1. INPUT'!E10 | E87: '1. INPUT'!F10 | F87: '1. INPUT'!G10 | G87: '1. INPUT'!H10 | H87: =SUM(C87:G87)*52
B88: 2 | C88: '1. INPUT'!D11 | D88: '1. INPUT'!E11 | E88: '1. INPUT'!F11 | F88: '1. INPUT'!G11 | G88: '1. INPUT'!H11 | H88: =SUM(C88:G88)*52
B89: 3 | C89: '1. INPUT'!D12 | D89: '1. INPUT'!E12 | E89: '1. INPUT'!F12 | F89: '1. INPUT'!G12 | G89: '1. INPUT'!H12 | H89: =SUM(C89:G89)*52
B90: 4 | C90: '1. INPUT'!D13 | D90: '1. INPUT'!E13 | E90: '1. INPUT'!F13 | F90: '1. INPUT'!G13 | G90: '1. INPUT'!H13 | H90: =SUM(C90:G90)*52
B91: 5 | C91: '1. INPUT'!D14 | D91: '1. INPUT'!E14 | E91: '1. INPUT'!F14 | F91: '1. INPUT'!G14 | G91: '1. INPUT'!H14 | H91: =SUM(C91:G91)*52
B92: 6 | C92: '1. INPUT'!D15 | D92: '1. INPUT'!E15 | E92: '1. INPUT'!F15 | F92: '1. INPUT'!G15 | G92: '1. INPUT'!H15 | H92: =SUM(C92:G92)*52
B93: 7 | C93: '1. INPUT'!D16 | D93: '1. INPUT'!E16 | E93: '1. INPUT'!F16 | F93: '1. INPUT'!G16 | G93: '1. INPUT'!H16 | H93: =SUM(C93:G93)*52
B94: 8 | C94: '1. INPUT'!D17 | D94: '1. INPUT'!E17 | E94: '1. INPUT'!F17 | F94: '1. INPUT'!G17 | G94: '1. INPUT'!H17 | H94: =SUM(C94:G94)*52
A96: Minor Stops | B96: 1 | C96: '1. INPUT'!D10 | D96: '1. INPUT'!E10 | E96: '1. INPUT'!F10 | F96: '1. INPUT'!G10 | G96: '1. INPUT'!H10 | H96: =SUM(C96:G96)*52
B97: 2 | C97: '1. INPUT'!D11 | D97: '1. INPUT'!E11 | E97: '1. INPUT'!F11 | F97: '1. INPUT'!G11 | G97: '1. INPUT'!H11 | H97: =SUM(C97:G97)*52
B98: 3 | C98: '1. INPUT'!D12 | D98: '1. INPUT'!E12 | E98: '1. INPUT'!F12 | F98: '1. INPUT'!G12 | G98: '1. INPUT'!H12 | H98: =SUM(C98:G98)*52
B99: 4 | C99: '1. INPUT'!D13 | D99: '1. INPUT'!E13 | E99: '1. INPUT'!F13 | F99: '1. INPUT'!G13 | G99: '1. INPUT'!H13 | H99: =SUM(C99:G99)*52
B100: 5 | C100: '1. INPUT'!D14 | D100: '1. INPUT'!E14 | E100: '1. INPUT'!F14 | F100: '1. INPUT'!G14 | G100: '1. INPUT'!H14 | H100: =SUM(C100:G100)*52
B101: 6 | C101: '1. INPUT'!D15 | D101: '1. INPUT'!E15 | E101: '1. INPUT'!F15 | F101: '1. INPUT'!G15 | G101: '1. INPUT'!H15 | H101: =SUM(C101:G101)*52
B102: 7 | C102: '1. INPUT'!D16 | D102: '1. INPUT'!E16 | E102: '1. INPUT'!F16 | F102: '1. INPUT'!G16 | G102: '1. INPUT'!H16 | H102: =SUM(C102:G102)*52
B103: 8 | C103: '1. INPUT'!D17 | D103: '1. INPUT'!E17 | E103: '1. INPUT'!F17 | F103: '1. INPUT'!G17 | G103: '1. INPUT'!H17 | H103: =SUM(C103:G103)*52
A105: TOTAL ANNUAL OPPORTUNITY | H105: =SUM(H6:H104)

Sheet 4. DOLLAR_MATRIX
A1: 4. Dollar Value Matrix
A3: Prepared for: EG SEOW
A5: Product | B5: Weekly Volume | C5: Weekly CM (RM) | D5: Annual Volume | E5: Annual CM (RM) | F5: Annual Rank | G5: Notes
A6: '1. INPUT'!B10 | B6: =SUM('1. INPUT'!D10:H10) | C6: =B6*'1. INPUT'!J10 | D6: =B6*52 | E6: =C6*52 | F6: =RANK(E6,E$6:E$13,0) | G6: See INPUT sheet for details
A7: '1. INPUT'!B11 | B7: =SUM('1. INPUT'!D11:H11) | C7: =B7*'1. INPUT'!J11 | D7: =B7*52 | E7: =C7*52 | F7: =RANK(E7,E$6:E$13,0) | G7: See INPUT sheet for details
A8: '1. INPUT'!B12 | B8: =SUM('1. INPUT'!D12:H12) | C8: =B8*'1. INPUT'!J12 | D8: =B8*52 | E8: =C8*52 | F8: =RANK(E8,E$6:E$13,0) | G8: See INPUT sheet for details
A9: '1. INPUT'!B13 | B9: =SUM('1. INPUT'!D13:H13) | C9: =B9*'1. INPUT'!J13 | D9: =B9*52 | E9: =C9*52 | F9: =RANK(E9,E$6:E$13,0) | G9: See INPUT sheet for details
A10: '1. INPUT'!B14 | B10: =SUM('1. INPUT'!D14:H14) | C10: =B10*'1. INPUT'!J14 | D10: =B10*52 | E10: =C10*52 | F10: =RANK(E10,E$6:E$13,0) | G10: See INPUT sheet for details
A11: '1. INPUT'!B15 | B11: =SUM('1. INPUT'!D15:H15) | C11: =B11*'1. INPUT'!J15 | D11: =B11*52 | E11: =C11*52 | F11: =RANK(E11,E$6:E$13,0) | G11: See INPUT sheet for details
A12: '1. INPUT'!B16 | B12: =SUM('1. INPUT'!D16:H16) | C12: =B12*'1. INPUT'!J16 | D12: =B12*52 | E12: =C12*52 | F12: =RANK(E12,E$6:E$13,0) | G12: See INPUT sheet for details
A13: '1. INPUT'!B17 | B13: =SUM('1. INPUT'!D17:H17) | C13: =B13*'1. INPUT'!J17 | D13: =B13*52 | E13: =C13*52 | F13: =RANK(E13,E$6:E$13,0) | G13: See INPUT sheet for details
A14: TOTAL | B14: =SUM(B6:B13) | E14: =SUM(E6:E13)

Sheet 5. SUMMARY
A1: 5. Executive Summary & Recommendations
A3: Prepared for: EG SEOW / Founder, OAKAI SDN BHD
A5: Diagnostic Metric | B5: Current | C5: Target | D5: Gap | E5: Status
A6: Total Annual $ Opportunity | B6: ='3. LOSS_ANALYSIS'!H105 | C6: ≥ RM 500,000 | D6: Gap | E6: 🔴 Critical
A7: Top Loss Category | B7: USDT - Machine Failure (per Rev15) | C7: Reduce by 30% | D7: Gap | E7: 🔴 Urgent
A8: Top Revenue Product | B8: See DOLLAR_MATRIX | C8: Maximize volume | D8: Gap | E8: 🟡 Monitor
A9: OEE Improvement Potential | B9: TBD | C9: 5-15% pts | D9: Gap | E9: 🟢 Opportunity
A10: Project Payback Period | B10: TBD | C10: < 6 months | D10: Gap | E10: 🟢 Attractive ROI
A13: Top 5 Priority Actions:
A15: 1. Address Speed Loss — largest dollar impact per the analysis
A16: 2. Implement defect tracking at machine level (Quality Loss - Defect)
A17: 3. Optimize changeover times to reduce USDT - Machine Assist
A18: 4. Set up daily production dashboards linked to this model
A19: 5. Engage maintenance team to reduce USDT - Machine Failure root cause

Sheet 6. CHARTS
A1: 6. Charts & Visualizations
A3: Prepared for: EG SEOW
A5: Chart Descriptions (auto-generate from Sheets 1-4):
A6: Chart 1: Annual Opportunity by Loss Category (Vertical Bar)
A7: Chart 2: Contribution Margin Ranking (Waterfall)
A8: Chart 3: Product Volume Distribution (Pie)
A9: Chart 4: Weekly Volume Trend (Line)
B12: Opportunity by Category
B22: CM Waterfall
B32: Volume Pie
